allure/__init__.py
allure/adaptor.py
allure/common.py
allure/constants.py
allure/pytest_plugin.py
allure/rules.py
allure/structure.py
allure/utils.py
pytest_allure_adaptor2-1.8.2.dist-info/LICENSE
pytest_allure_adaptor2-1.8.2.dist-info/METADATA
pytest_allure_adaptor2-1.8.2.dist-info/WHEEL
pytest_allure_adaptor2-1.8.2.dist-info/entry_points.txt
pytest_allure_adaptor2-1.8.2.dist-info/top_level.txt
pytest_allure_adaptor2-1.8.2.dist-info/RECORD
