Metadata-Version: 2.1
Name: pytest-allure-adaptor2
Version: 1.8.2
Summary: Plugin for py.test to generate allure xml reports
Home-page: https://github.com/allure-framework/allure-pytest
Author: pupssman
Author-email: pupssman@yandex-team.ru
License: UNKNOWN
Platform: UNKNOWN
Requires-Dist: lxml (>=3.2.0)
Requires-Dist: pytest (>=2.7.3)
